configs/.secrets.examples.toml
configs/__init__.py
configs/config.py
configs/settings.toml
fusepystarter/__init__.py
fusepystarter/cookiecutter/__init__.py
fusepystarter/cookiecutter/packaging.py
fusepystarter/decorators/__init__.py
fusepystarter/decorators/logging_service.py
fusepystarter-0.1.7.dist-info/METADATA
fusepystarter-0.1.7.dist-info/WHEEL
fusepystarter-0.1.7.dist-info/entry_points.txt
fusepystarter-0.1.7.dist-info/licenses/AUTHORS.rst
fusepystarter-0.1.7.dist-info/licenses/LICENSE
fusepystarter-0.1.7.dist-info/RECORD
