Metadata-Version: 2.4
Name: fusepystarter
Version: 0.1.7
Summary: A modern Python project forge with pre-configured tooling and CI/CD.
Project-URL: Homepage, https://sunil-fm.github.io/FusePyStarter/
Project-URL: Repository, https://github.com/sunil-fm/FusePyStarter
Project-URL: Documentation, https://sunil-fm.github.io/FusePyStarter/
Project-URL: Changelog, https://github.com/sunil-fm/FusePyStarter/CHANGELOG.rst
Project-URL: Releases, https://github.com/sunil-fm/FusePyStarter/releases
Author-email: Sunil Ghimire <sunil.ghimire@fusemachines.com>
License-File: AUTHORS.rst
License-File: LICENSE
Classifier: Development Status :: 2 - Pre-Alpha
Classifier: Intended Audience :: Developers
Classifier: License :: OSI Approved :: MIT License
Classifier: Natural Language :: English
Classifier: Programming Language :: Python
Classifier: Programming Language :: Python :: 3 :: Only
Classifier: Programming Language :: Python :: 3.8
Classifier: Programming Language :: Python :: 3.9
Classifier: Programming Language :: Python :: 3.10
Classifier: Programming Language :: Python :: 3.11
Classifier: Programming Language :: Python :: 3.12
Classifier: Programming Language :: Python :: 3.13
Requires-Python: >=3.12
Requires-Dist: cookiecutter>=2.6.0
Requires-Dist: dynaconf>=3.2.11
Requires-Dist: fire>=0.7.0
Requires-Dist: setuptools>=80.9.0
Requires-Dist: toml>=0.10.2
